Workbook

Sheet 0. Cover Page
A1: ENTERPRISE GRC MANAGEMENT SYSTEM
A3: Governance, Risk & Compliance Portfolio
A5: Version: 2.0
A6: Date: 2026/07/29
A8: Prepared by: Lindiwe Lee Mthembu
A9: Department: Risk Management
A11: © 2026 All Rights Reserved

Sheet 1. User Guide
A1: USER GUIDE - GRC MANAGEMENT SYSTEM
A3: Sheet Name | B3: Description | C3: Key Columns
A4: 2. Risk Register | B4: All enterprise risks with inherent & residual scores | C4: RiskID, Category, Inherent, Residual, Status
A5: 3. Control Library | B5: All controls mapped to risks and frameworks | C5: ControlID, RiskID, Type, Effectiveness
A6: 4. Incident Log | B6: Security and compliance incidents | C6: IncidentID, Type, Severity, Status, Cost
A7: 5. Audit Schedule | B7: Internal/external audit calendar | C7: AuditID, Type, Scope, Status, Findings
A8: 6. Vendor Risk | B8: Third-party vendor risk assessments | C8: VendorID, Category, RiskScore, Status
A9: 7. Policy Manager | B9: Policies with review dates and approval | C9: PolicyID, Status, ReviewDate, Owner
A10: 8. Framework Mapping | B10: ISO 27001, NIST, POPIA, PCI DSS mapping | C10: Framework, Control, Status
A11: 9. Executive Dashboard | B11: KPI cards, charts, heat map | C11: All key metrics
A12: 10. Risk Heat Map | B12: 5x5 dynamic risk visualization | C12: Likelihood x Impact

Sheet 2. Risk Register
A1: RiskID | B1: Risk Category | C1: Risk Description | D1: Inherent Likelihood (1-5) | E1: Inherent Impact (1-5) | F1: Inherent Score | G1: Control Effectiveness (%) | H1: Residual Likelihood | I1: Residual Impact | J1: Residual Score | K1: Risk Owner | L1: Status | M1: Last Review | N1: Next Review | O1: Risk Level
A2: RISK-001 | B2: Human Resources | C2: Project delay | D2: 3 | E2: 2 | F2: 6 | G2: 0.44 | H2: 1.7 | I2: 1.1 | J2: 1.9 | K2: CISO | L2: Transfered | M2: 45954 | N2: 46530 | O2: Critical
A3: RISK-002 | B3: Human Resources | C3: Ransomware attack | D3: 3 | E3: 5 | F3: 15 | G3: 0.84 | H3: 1 | I3: 1 | J3: 1 | K3: Head of HR | L3: Mitigated | M3: 45913 | N3: 46253 | O3: Critical
A4: RISK-003 | B4: Strategic | C4: Pandemic | D4: 3 | E4: 4 | F4: 12 | G4: 0.24 | H4: 2.3 | I4: 3 | J4: 6.9 | K4: CEO | L4: Accepted | M4: 46123 | N4: 46460 | O4: Medium
A5: RISK-004 | B5: Technology | C5: Third-party failure | D5: 2 | E5: 5 | F5: 10 | G5: 0.86 | H5: 1 | I5: 1 | J5: 1 | K5: Head of HR | L5: Accepted | M5: 45899 | N5: 46315 | O5: Medium
A6: RISK-005 | B6: Technology | C6: DDoS attack | D6: 2 | E6: 3 | F6: 6 | G6: 0.28 | H6: 1.4 | I6: 2.2 | J6: 3.1 | K6: CIO | L6: Monitoring | M6: 46226 | N6: 46442 | O6: Medium
A7: RISK-006 | B7: Data Privacy | C7: Cloud misconfiguration | D7: 4 | E7: 2 | F7: 8 | G7: 0.23 | H7: 3.1 | I7: 1.5 | J7: 4.6 | K7: COO | L7: Mitigated | M7: 46122 | N7: 46579 | O7: Medium
A8: RISK-007 | B8: Strategic | C8: Market volatility | D8: 2 | E8: 1 | F8: 2 | G8: 0.33 | H8: 1.3 | I8: 1 | J8: 1.3 | K8: CEO | L8: Transfered | M8: 46081 | N8: 46493 | O8: Medium
A9: RISK-008 | B9: Financial | C9: Harassment claim | D9: 2 | E9: 1 | F9: 2 | G9: 0.67 | H9: 1 | I9: 1 | J9: 1 | K9: CEO | L9: Active | M9: 45901 | N9: 46328 | O9: Medium
A10: RISK-009 | B10: Human Resources | C10: Pandemic | D10: 2 | E10: 5 | F10: 10 | G10: 0.71 | H10: 1 | I10: 1.4 | J10: 1.4 | K10: CEO | L10: Transfered | M10: 46196 | N10: 46437 | O10: Medium
A11: RISK-010 | B11: Technology | C11: Sanctions breach | D11: 5 | E11: 1 | F11: 5 | G11: 0.64 | H11: 1.8 | I11: 1 | J11: 1.8 | K11: CEO | L11: Monitoring | M11: 45984 | N11: 46416 | O11: Medium
A12: RISK-011 | B12: Third-Party | C12: Credit risk | D12: 2 | E12: 3 | F12: 6 | G12: 0.41 | H12: 1.2 | I12: 1.8 | J12: 2.2 | K12: CFO | L12: Active | M12: 45874 | N12: 46255 | O12: Medium
A13: RISK-012 | B13: Financial | C13: Pandemic | D13: 3 | E13: 1 | F13: 3 | G13: 0.58 | H13: 1.3 | I13: 1 | J13: 1.3 | K13: CIO | L13: Mitigated | M13: 46034 | N13: 46290 | O13: Medium
... A221: RISK-220 | B221: Legal | C221: Regulatory fine | D221: 3 | E221: 2 | F221: 6 | G221: 0.33 | H221: 2 | I221: 1.3 | J221: 2.6 | K221: CISO | L221: Transfered | M221: 45956 | N221: 46421 | O221: Medium

Sheet 3. Control Library
A1: ControlID | B1: Control Name | C1: Control Type | D1: RiskID | E1: Framework | F1: Effectiveness | G1: Implementation Date | H1: Owner | I1: Status
A2: CTRL-001 | B2: Control Self-Assessment | C2: Directive | D2: RISK-150 | E2: GDPR | F2: 0.34 | G2: 46132 | H2: Head of Legal | I2: Monitoring
A3: CTRL-002 | B3: Secure SDLC | C3: Preventive | D3: RISK-075 | E3: NIST CSF | F3: 0.22 | G3: 46196 | H3: CTO | I3: Transfered
A4: CTRL-003 | B4: External Audit | C4: Preventive | D4: RISK-201 | E4: SOC 2 | F4: 0.83 | G4: 46142 | H4: CIO | I4: Accepted
A5: CTRL-004 | B5: MFA | C5: Detective | D5: RISK-174 | E5: NIST 800-53 | F5: 0.92 | G5: 45934 | H5: CIO | I5: Accepted
A6: CTRL-005 | B6: MFA | C6: Preventive | D6: RISK-136 | E6: NIST 800-53 | F6: 0.38 | G6: 45963 | H6: CIO | I6: Monitoring
A7: CTRL-006 | B7: Privacy Policy | C7: Preventive | D7: RISK-179 | E7: HITRUST | F7: 0.63 | G7: 46138 | H7: CFO | I7: Active
A8: CTRL-007 | B8: Contract Review | C8: Directive | D8: RISK-014 | E8: HITRUST | F8: 0.97 | G8: 46063 | H8: CTO | I8: Transfered
A9: CTRL-008 | B9: BCP | C9: Preventive | D9: RISK-178 | E9: SOC 2 | F9: 0.61 | G9: 45952 | H9: CEO | I9: Mitigated
A10: CTRL-009 | B10: Risk Assessment | C10: Detective | D10: RISK-168 | E10: HITRUST | F10: 0.7 | G10: 46085 | H10: CISO | I10: Mitigated
A11: CTRL-010 | B11: Security Awareness | C11: Corrective | D11: RISK-090 | E11: NIST CSF | F11: 0.69 | G11: 45888 | H11: CEO | I11: Transfered
A12: CTRL-011 | B12: License Management | C12: Preventive | D12: RISK-108 | E12: NIST CSF | F12: 0.33 | G12: 45948 | H12: Head of HR | I12: Active
A13: CTRL-012 | B13: Data Subject Request | C13: Corrective | D13: RISK-114 | E13: HITRUST | F13: 0.92 | G13: 46001 | H13: CTO | I13: Monitoring
... A451: CTRL-450 | B451: Contract Review | C451: Detective | D451: RISK-043 | E451: NIST 800-53 | F451: 0.73 | G451: 45931 | H451: CTO | I451: Monitoring

Sheet 4. Incident Log
A1: IncidentID | B1: Date | C1: Type | D1: Description | E1: Severity (1-5) | F1: Status | G1: Impact (Financial) | H1: Root Cause | I1: Resolution Date | J1: Lessons Learned
A2: INC-001 | B2: 46100 | C2: Ransomware | D2: Incident description 1 | E2: 4 | F2: Monitoring | G2: 268012 | H2: Cause 6 | I2: 46206 | J2: Improvement 1
A3: INC-002 | B3: 46040 | C3: Security Breach | D3: Incident description 2 | E3: 4 | F3: Transfered | G3: 249458 | H3: Cause 7 | I3: 46225 | J3: Improvement 2
A4: INC-003 | B4: 45724 | C4: Fraud | D4: Incident description 3 | E4: 1 | F4: Mitigated | G4: 398250 | H4: Cause 9 | I4: 46208 | J4: Improvement 3
A5: INC-004 | B5: 45734 | C5: Security Breach | D5: Incident description 4 | E5: 1 | F5: Transfered | G5: 50578 | H5: Cause 3 | I5: 46226 | J5: Improvement 4
A6: INC-005 | B6: 45686 | C6: Phishing | D6: Incident description 5 | E6: 4 | F6: Accepted | G6: 358256 | H6: Cause 8 | I6: 46204 | J6: Improvement 5
A7: INC-006 | B7: 46230 | C7: System Outage | D7: Incident description 6 | E7: 5 | F7: Transfered | G7: 141429 | H7: Cause 3 | I7: 46203 | J7: Improvement 6
A8: INC-007 | B8: 46120 | C8: DDoS | D8: Incident description 7 | E8: 3 | F8: Active | G8: 266227 | H8: Cause 6 | I8: 46206 | J8: Improvement 7
A9: INC-008 | B9: 45552 | C9: System Outage | D9: Incident description 8 | E9: 5 | F9: Monitoring | G9: 103368 | H9: Cause 10 | I9: 46223 | J9: Improvement 8
A10: INC-009 | B10: 45905 | C10: Security Breach | D10: Incident description 9 | E10: 1 | F10: Mitigated | G10: 456999 | H10: Cause 7 | I10: 46213 | J10: Improvement 9
A11: INC-010 | B11: 45766 | C11: Malware | D11: Incident description 10 | E11: 2 | F11: Monitoring | G11: 499092 | H11: Cause 4 | I11: 46207 | J11: Improvement 10
A12: INC-011 | B12: 46229 | C12: Phishing | D12: Incident description 11 | E12: 1 | F12: Accepted | G12: 368798 | H12: Cause 1 | I12: 46207 | J12: Improvement 11
A13: INC-012 | B13: 45868 | C13: Ransomware | D13: Incident description 12 | E13: 2 | F13: Active | G13: 179544 | H13: Cause 5 | I13: 46217 | J13: Improvement 12
... A101: INC-100 | B101: 46139 | C101: DDoS | D101: Incident description 100 | E101: 5 | F101: Mitigated | G101: 263154 | H101: Cause 1 | I101: 46202 | J101: Improvement 100

Sheet 5. Audit Schedule
A1: AuditID | B1: Audit Type | C1: Scope | D1: Auditor | E1: Start Date | F1: End Date | G1: Status | H1: Findings Count | I1: Critical Findings | J1: Audit Report
A2: AUDIT-001 | B2: PCI DSS | C2: Scope 1 | D2: Auditor 7 | E2: 46254 | F2: 46277 | G2: Monitoring | H2: 19 | I2: 3 | J2: Report 1
A3: AUDIT-002 | B3: IT General | C3: Scope 2 | D3: Auditor 5 | E3: 46486 | F3: 46495 | G3: Mitigated | H3: 17 | I3: 1 | J3: Report 2
A4: AUDIT-003 | B4: PCI DSS | C4: Scope 3 | D4: Auditor 10 | E4: 46361 | F4: 46370 | G4: Mitigated | H4: 8 | I4: 3 | J4: Report 3
A5: AUDIT-004 | B5: Regulatory | C5: Scope 4 | D5: Auditor 1 | E5: 46306 | F5: 46324 | G5: Monitoring | H5: 13 | I5: 0 | J5: Report 4
A6: AUDIT-005 | B6: Financial | C6: Scope 5 | D6: Auditor 9 | E6: 46538 | F6: 46568 | G6: Active | H6: 2 | I6: 1 | J6: Report 5
A7: AUDIT-006 | B7: Financial | C7: Scope 6 | D7: Auditor 5 | E7: 46465 | F7: 46470 | G7: Accepted | H7: 10 | I7: 3 | J7: Report 6
A8: AUDIT-007 | B8: Financial | C8: Scope 7 | D8: Auditor 8 | E8: 46377 | F8: 46384 | G8: Mitigated | H8: 0 | I8: 1 | J8: Report 7
A9: AUDIT-008 | B9: Financial | C9: Scope 8 | D9: Auditor 8 | E9: 46533 | F9: 46546 | G9: Mitigated | H9: 20 | I9: 3 | J9: Report 8
A10: AUDIT-009 | B10: Internal | C10: Scope 9 | D10: Auditor 7 | E10: 46389 | F10: 46418 | G10: Transfered | H10: 12 | I10: 4 | J10: Report 9
A11: AUDIT-010 | B11: Internal | C11: Scope 10 | D11: Auditor 7 | E11: 46512 | F11: 46517 | G11: Active | H11: 20 | I11: 4 | J11: Report 10
A12: AUDIT-011 | B12: NIST CSF | C12: Scope 11 | D12: Auditor 8 | E12: 46274 | F12: 46287 | G12: Active | H12: 15 | I12: 3 | J12: Report 11
A13: AUDIT-012 | B13: SOC 2 | C13: Scope 12 | D13: Auditor 9 | E13: 46405 | F13: 46419 | G13: Monitoring | H13: 11 | I13: 1 | J13: Report 12
... A61: AUDIT-060 | B61: SOC 2 | C61: Scope 60 | D61: Auditor 8 | E61: 46326 | F61: 46333 | G61: Accepted | H61: 7 | I61: 4 | J61: Report 60

Sheet 6. Vendor Risk
A1: VendorID | B1: Vendor Name | C1: Category | D1: Criticality | E1: Risk Score | F1: Status | G1: Last Assessment | H1: Next Assessment | I1: Compliance Status
A2: VENDOR-001 | B2: CyberShield 1 | C2: Third-Party | D2: Medium | E2: 64.699997 | F2: Active | G2: 45991 | H2: 46302 | I2: Accepted
A3: VENDOR-002 | B3: Atlassian 2 | C3: Cybersecurity | D3: High | E3: 27.200001 | F3: Active | G3: 46003 | H3: 46044 | I3: Accepted
A4: VENDOR-003 | B4: PwC 3 | C4: Legal | D4: Critical | E4: 10.5 | F4: Transfered | G4: 45951 | H4: 45974 | I4: Transfered
A5: VENDOR-004 | B5: Deloitte 4 | C5: Legal | D5: Medium | E5: 77.199997 | F5: Accepted | G5: 45694 | H5: 45922 | I5: Transfered
A6: VENDOR-005 | B6: SentinelOne 5 | C6: Technology | D6: Critical | E6: 35.400002 | F6: Active | G6: 45948 | H6: 46035 | I6: Transfered
A7: VENDOR-006 | B7: GRCInsight 6 | C7: Strategic | D7: Medium | E7: 30.200001 | F7: Accepted | G7: 45728 | H7: 45859 | I7: Transfered
A8: VENDOR-007 | B8: PwC 7 | C8: Human Resources | D8: High | E8: 43.099998 | F8: Accepted | G8: 45636 | H8: 45986 | I8: Accepted
A9: VENDOR-008 | B9: Slack 8 | C9: Financial | D9: High | E9: 28.700001 | F9: Mitigated | G9: 46033 | H9: 46041 | I9: Accepted
A10: VENDOR-009 | B10: ServiceNow 9 | C10: Legal | D10: Low | E10: 51 | F10: Active | G10: 45948 | H10: 45968 | I10: Transfered
A11: VENDOR-010 | B11: GRCInsight 10 | C11: Strategic | D11: Medium | E11: 56 | F11: Mitigated | G11: 45627 | H11: 45836 | I11: Active
A12: VENDOR-011 | B12: Google Cloud 11 | C12: Data Privacy | D12: Medium | E12: 99.300003 | F12: Transfered | G12: 46174 | H12: 46396 | I12: Mitigated
A13: VENDOR-012 | B13: Salesforce 12 | C13: Operational | D13: High | E13: 27.200001 | F13: Transfered | G13: 45532 | H13: 45610 | I13: Active
... A81: VENDOR-080 | B81: EY 80 | C81: Financial | D81: Medium | E81: 80.400002 | F81: Mitigated | G81: 45605 | H81: 45622 | I81: Active

Sheet 7. Policy Manager
A1: PolicyID | B1: Policy Name | C1: Version | D1: Status | E1: Approval Date | F1: Review Date | G1: Next Review | H1: Owner | I1: Framework
A2: POL-001 | B2: Awareness Policy | C2: v3.2 | D2: Accepted | E2: 46076 | F2: 46391 | G2: 46756 | H2: CISO | I2: NIST 800-53
A3: POL-002 | B3: Mobile Device Policy | C3: v1.5 | D3: Mitigated | E3: 46042 | F3: 46067 | G3: 46432 | H3: Head of Legal | I3: NIST CSF
A4: POL-003 | B4: Awareness Policy | C4: v5.4 | D4: Active | E4: 46081 | F4: 46297 | G4: 46662 | H4: CTO | I4: HITRUST
A5: POL-004 | B5: Mobile Device Policy | C5: v2.7 | D5: Monitoring | E5: 45692 | F5: 46009 | G5: 46374 | H5: CTO | I5: SOC 2
A6: POL-005 | B6: Physical Security Policy | C6: v1.5 | D6: Active | E6: 45549 | F6: 45612 | G6: 45977 | H6: CIO | I6: GDPR
A7: POL-006 | B7: Privacy Policy | C7: v1.8 | D7: Active | E7: 45675 | F7: 45713 | G7: 46078 | H7: DPO | I7: NIST CSF
A8: POL-007 | B8: Acceptable Use Policy | C8: v5.7 | D8: Accepted | E8: 45811 | F8: 45842 | G8: 46207 | H8: CEO | I8: NIST CSF
A9: POL-008 | B9: BCP Policy | C9: v5.1 | D9: Transfered | E9: 45774 | F9: 46093 | G9: 46458 | H9: CTO | I9: SOC 2
A10: POL-009 | B10: Training Policy | C10: v2.1 | D10: Transfered | E10: 45828 | F10: 45846 | G10: 46211 | H10: Head of Legal | I10: GDPR
A11: POL-010 | B11: Compliance Policy | C11: v1.9 | D11: Active | E11: 45585 | F11: 45776 | G11: 46141 | H11: CRO | I11: NIST CSF
A12: POL-011 | B12: Compliance Policy | C12: v2.4 | D12: Monitoring | E12: 45835 | F12: 45849 | G12: 46214 | H12: CISO | I12: ISO 27001:2022
A13: POL-012 | B13: Bring Your Own Device | C13: v3.8 | D13: Accepted | E13: 45985 | F13: 46224 | G13: 46589 | H13: CIO | I13: NIST CSF
... A51: POL-050 | B51: Asset Management Policy | C51: v4.5 | D51: Monitoring | E51: 45743 | F51: 46047 | G51: 46412 | H51: CIO | I51: HITRUST

Sheet 8. Framework Mapping
A1: Framework | B1: Control | C1: Control ID | D1: Mapped Risk ID | E1: Implementation Status | F1: Evidence
A2: GDPR | B2: A.5.2 | C2: CTRL-081 | D2: RISK-210 | E2: Accepted | F2: Evidence 1
A3: NIST 800-53 | B3: A.14.1 | C3: CTRL-091 | D3: RISK-055 | E3: Mitigated | F3: Evidence 2
A4: POPIA | B4: A.5.1 | C4: CTRL-027 | D4: RISK-013 | E4: Transfered | F4: Evidence 3
A5: NIST CSF | B5: A.5.1 | C5: CTRL-123 | D5: RISK-183 | E5: Monitoring | F5: Evidence 4
A6: NIST 800-53 | B6: A.10.1 | C6: CTRL-017 | D6: RISK-186 | E6: Mitigated | F6: Evidence 5
A7: POPIA | B7: A.13.1 | C7: CTRL-063 | D7: RISK-097 | E7: Active | F7: Evidence 6
A8: POPIA | B8: A.14.1 | C8: CTRL-144 | D8: RISK-208 | E8: Transfered | F8: Evidence 7
A9: ISO 27001:2022 | B9: A.16.1 | C9: CTRL-009 | D9: RISK-067 | E9: Mitigated | F9: Evidence 8
A10: GDPR | B10: A.5.1 | C10: CTRL-075 | D10: RISK-120 | E10: Transfered | F10: Evidence 9
A11: GDPR | B11: A.5.2 | C11: CTRL-025 | D11: RISK-029 | E11: Accepted | F11: Evidence 10
A12: NIST CSF | B12: A.10.1 | C12: CTRL-095 | D12: RISK-012 | E12: Active | F12: Evidence 11
... A101: SOC 2 | B101: A.5.1 | C101: CTRL-039 | D101: RISK-030 | E101: Mitigated | F101: Evidence 100

Sheet 9. Executive Dashboard
A1: ENTERPRISE GRC DASHBOARD
D2: Category | E2: Count | F2: Avg Residual | G2: 5 | H2: Likelihood ? | I2: =COUNTIFS('2. Risk Register'!H:H,2,'2. Risk Register'!I:I,5) -> 0 | J2: =COUNTIFS('2. Risk Register'!H:H,3,'2. Risk Register'!I:I,5) -> 0 | K2: =COUNTIFS('2. Risk Register'!H:H,4,'2. Risk Register'!I:I,5) -> 0 | L2: =COUNTIFS('2. Risk Register'!H:H,5,'2. Risk Register'!I:I,5) -> 0
A3: Total Risks | B3: =COUNTA('2. Risk Register'!A:A)-1 -> 220 | D3: Cybersecurity | E3: =COUNTIF('2. Risk Register'!B:B,"Cybersecurity") -> 20 | F3: =AVERAGEIF('2. Risk Register'!B:B,"Cybersecurity",'2. Risk Register'!J:J) -> 3.11 | G3: Impact ? | H3: =COUNTIFS('2. Risk Register'!H:H,1,'2. Risk Register'!I:I,4) -> 0 | I3: =COUNTIFS('2. Risk Register'!H:H,2,'2. Risk Register'!I:I,4) -> 0 | J3: =COUNTIFS('2. Risk Register'!H:H,3,'2. Risk Register'!I:I,4) -> 0 | K3: =COUNTIFS('2. Risk Register'!H:H,4,'2. Risk Register'!I:I,4) -> 0 | L3: =COUNTIFS('2. Risk Register'!H:H,5,'2. Risk Register'!I:I,4) -> 0
A4: Critical Risks | B4: =COUNTIF('2. Risk Register'!O:O,"Critical") -> 2 | D4: Data Privacy | E4: =COUNTIF('2. Risk Register'!B:B,"Data Privacy") -> 24 | F4: =AVERAGEIF('2. Risk Register'!B:B,"Data Privacy",'2. Risk Register'!J:J) -> 1.8916667 | G4: 3 | H4: =COUNTIFS('2. Risk Register'!H:H,1,'2. Risk Register'!I:I,3) -> 2 | I4: =COUNTIFS('2. Risk Register'!H:H,2,'2. Risk Register'!I:I,3) -> 0 | J4: =COUNTIFS('2. Risk Register'!H:H,3,'2. Risk Register'!I:I,3) -> 1 | K4: =COUNTIFS('2. Risk Register'!H:H,4,'2. Risk Register'!I:I,3) -> 0 | L4: =COUNTIFS('2. Risk Register'!H:H,5,'2. Risk Register'!I:I,3) -> 0
A5: Open Incidents | B5: =COUNTIF('4. Incident Log'!F:F,"Active") -> 22 | D5: Operational | E5: =COUNTIF('2. Risk Register'!B:B,"Operational") -> 24 | F5: =AVERAGEIF('2. Risk Register'!B:B,"Operational",'2. Risk Register'!J:J) -> 2.5125 | G5: 2 | H5: =COUNTIFS('2. Risk Register'!H:H,1,'2. Risk Register'!I:I,2) -> 3 | I5: =COUNTIFS('2. Risk Register'!H:H,2,'2. Risk Register'!I:I,2) -> 0 | J5: =COUNTIFS('2. Risk Register'!H:H,3,'2. Risk Register'!I:I,2) -> 0 | K5: =COUNTIFS('2. Risk Register'!H:H,4,'2. Risk Register'!I:I,2) -> 0 | L5: =COUNTIFS('2. Risk Register'!H:H,5,'2. Risk Register'!I:I,2) -> 0
A6: Compliance Rate | B6: =COUNTIF('8. Framework Mapping'!E:E,"Mitigated")/(COUNTA('8. Framework Mapping'!E:E)-1) -> 0.27 | D6: Financial | E6: =COUNTIF('2. Risk Register'!B:B,"Financial") -> 27 | F6: =AVERAGEIF('2. Risk Register'!B:B,"Financial",'2. Risk Register'!J:J) -> 2.1481481 | G6: 1 | H6: =COUNTIFS('2. Risk Register'!H:H,1,'2. Risk Register'!I:I,1) -> 82 | I6: =COUNTIFS('2. Risk Register'!H:H,2,'2. Risk Register'!I:I,1) -> 2 | J6: =COUNTIFS('2. Risk Register'!H:H,3,'2. Risk Register'!I:I,1) -> 0 | K6: =COUNTIFS('2. Risk Register'!H:H,4,'2. Risk Register'!I:I,1) -> 0 | L6: =COUNTIFS('2. Risk Register'!H:H,5,'2. Risk Register'!I:I,1) -> 0
A7: Vendors Assessed | B7: =COUNTA('6. Vendor Risk'!A:A)-1 -> 80 | D7: Compliance | E7: =COUNTIF('2. Risk Register'!B:B,"Compliance") -> 22 | F7: =AVERAGEIF('2. Risk Register'!B:B,"Compliance",'2. Risk Register'!J:J) -> 2.25
D8: Third-Party | E8: =COUNTIF('2. Risk Register'!B:B,"Third-Party") -> 18 | F8: =AVERAGEIF('2. Risk Register'!B:B,"Third-Party",'2. Risk Register'!J:J) -> 2.7666667
D9: Technology | E9: =COUNTIF('2. Risk Register'!B:B,"Technology") -> 23 | F9: =AVERAGEIF('2. Risk Register'!B:B,"Technology",'2. Risk Register'!J:J) -> 2.7956522
D10: Human Resources | E10: =COUNTIF('2. Risk Register'!B:B,"Human Resources") -> 24 | F10: =AVERAGEIF('2. Risk Register'!B:B,"Human Resources",'2. Risk Register'!J:J) -> 2.2916667
D11: Legal | E11: =COUNTIF('2. Risk Register'!B:B,"Legal") -> 15 | F11: =AVERAGEIF('2. Risk Register'!B:B,"Legal",'2. Risk Register'!J:J) -> 1.6
D12: Strategic | E12: =COUNTIF('2. Risk Register'!B:B,"Strategic") -> 23 | F12: =AVERAGEIF('2. Risk Register'!B:B,"Strategic",'2. Risk Register'!J:J) -> 3.0826087

Sheet 10. Risk Heat Map
A1: DETAILED RISK HEAT MAP
B2: 1 | C2: 2 | D2: 3 | E2: 4 | F2: 5
A3: 5 | B3: =COUNTIFS('2. Risk Register'!H:H,1,'2. Risk Register'!I:I,5) -> 0 | C3: =COUNTIFS('2. Risk Register'!H:H,2,'2. Risk Register'!I:I,5) -> 0 | D3: =COUNTIFS('2. Risk Register'!H:H,3,'2. Risk Register'!I:I,5) -> 0 | E3: =COUNTIFS('2. Risk Register'!H:H,4,'2. Risk Register'!I:I,5) -> 0 | F3: =COUNTIFS('2. Risk Register'!H:H,5,'2. Risk Register'!I:I,5) -> 0
A4: 4 | B4: =COUNTIFS('2. Risk Register'!H:H,1,'2. Risk Register'!I:I,4) -> 0 | C4: =COUNTIFS('2. Risk Register'!H:H,2,'2. Risk Register'!I:I,4) -> 0 | D4: =COUNTIFS('2. Risk Register'!H:H,3,'2. Risk Register'!I:I,4) -> 0 | E4: =COUNTIFS('2. Risk Register'!H:H,4,'2. Risk Register'!I:I,4) -> 0 | F4: =COUNTIFS('2. Risk Register'!H:H,5,'2. Risk Register'!I:I,4) -> 0
A5: 3 | B5: =COUNTIFS('2. Risk Register'!H:H,1,'2. Risk Register'!I:I,3) -> 2 | C5: =COUNTIFS('2. Risk Register'!H:H,2,'2. Risk Register'!I:I,3) -> 0 | D5: =COUNTIFS('2. Risk Register'!H:H,3,'2. Risk Register'!I:I,3) -> 1 | E5: =COUNTIFS('2. Risk Register'!H:H,4,'2. Risk Register'!I:I,3) -> 0 | F5: =COUNTIFS('2. Risk Register'!H:H,5,'2. Risk Register'!I:I,3) -> 0
A6: 2 | B6: =COUNTIFS('2. Risk Register'!H:H,1,'2. Risk Register'!I:I,2) -> 3 | C6: =COUNTIFS('2. Risk Register'!H:H,2,'2. Risk Register'!I:I,2) -> 0 | D6: =COUNTIFS('2. Risk Register'!H:H,3,'2. Risk Register'!I:I,2) -> 0 | E6: =COUNTIFS('2. Risk Register'!H:H,4,'2. Risk Register'!I:I,2) -> 0 | F6: =COUNTIFS('2. Risk Register'!H:H,5,'2. Risk Register'!I:I,2) -> 0
A7: 1 | B7: =COUNTIFS('2. Risk Register'!H:H,1,'2. Risk Register'!I:I,1) -> 82 | C7: =COUNTIFS('2. Risk Register'!H:H,2,'2. Risk Register'!I:I,1) -> 2 | D7: =COUNTIFS('2. Risk Register'!H:H,3,'2. Risk Register'!I:I,1) -> 0 | E7: =COUNTIFS('2. Risk Register'!H:H,4,'2. Risk Register'!I:I,1) -> 0 | F7: =COUNTIFS('2. Risk Register'!H:H,5,'2. Risk Register'!I:I,1) -> 0
A9: Detailed Risk List by Cell:

Sheet 11. Data Dictionary
A1: DATA DICTIONARY - GRC MANAGEMENT SYSTEM
A3: Table | B3: Field | C3: Data Type | D3: Description | E3: Sample Values
A4: Risk Register | B4: RiskID | C4: Text | D4: Unique identifier | E4: RISK-001
A5: Risk Register | B5: Risk Category | C5: Text | D5: Risk classification | E5: Cybersecurity
A6: Risk Register | B6: Inherent Score | C6: Number | D6: Likelihood x Impact | E6: 46047
A7: Risk Register | B7: Residual Score | C7: Number | D7: After controls applied | E7: 46047
A8: Risk Register | B8: Risk Level | C8: Text | D8: Critical/High/Medium/Low | E8: High
A9: Control Library | B9: ControlID | C9: Text | D9: Unique identifier | E9: CTRL-001
A10: Control Library | B10: Control Type | C10: Text | D10: Preventive/Detective/Corrective | E10: Preventive
A11: Control Library | B11: Effectiveness | C11: Percentage | D11: Control effectiveness | E11: 0.85
A12: Incident Log | B12: IncidentID | C12: Text | D12: Unique identifier | E12: INC-001
A13: Incident Log | B13: Severity | C13: Number | D13: 1-5 scale | E13: 3
A14: Incident Log | B14: Impact | C14: Currency | D14: Financial impact | E14: 50000
A15: Audit Schedule | B15: AuditID | C15: Text | D15: Unique identifier | E15: AUDIT-001
A16: Audit Schedule | B16: Findings Count | C16: Number | D16: Number of findings | E16: 5
A17: Vendor Risk | B17: VendorID | C17: Text | D17: Unique identifier | E17: VENDOR-001
A18: Vendor Risk | B18: Risk Score | C18: Number | D18: 0-100 scale | E18: 75
A19: Policy Manager | B19: PolicyID | C19: Text | D19: Unique identifier | E19: POL-001
A20: Policy Manager | B20: Version | C20: Text | D20: Version number | E20: v1.0
A21: Framework Mapping | B21: Framework | C21: Text | D21: Compliance framework | E21: ISO 27001
A22: Framework Mapping | B22: Implementation Status | C22: Text | D22: Active/Mitigated | E22: Mitigated

Sheet 12. Scenario Analysis
A1: WHAT-IF SCENARIO ANALYSIS
A3: Risk Type | B3: Current Score | C3: Control Improvement | D3: Projected Score | E3: Risk Reduction | F3: Status
A4: Third-Party | B4: 19.5 | C4: 0.23
